cli_configparser/__init__.py
cli_configparser/read_setting.py
cli_configparser-0.1.0.dist-info/LICENSE
cli_configparser-0.1.0.dist-info/METADATA
cli_configparser-0.1.0.dist-info/WHEEL
cli_configparser-0.1.0.dist-info/top_level.txt
cli_configparser-0.1.0.dist-info/RECORD
