Metadata-Version: 2.1
Name: cli-configparser
Version: 0.1.0
Summary: CLI utility for reading from .ini config files
Home-page: http://github.com/drgriffis/cli-configparser
Author: Denis Newman-Griffis
Author-email: denis.newman.griffis@gmail.com
License: UNKNOWN
Platform: UNKNOWN
Classifier: Programming Language :: Python :: 3
Classifier: License :: OSI Approved :: MIT License
Classifier: Operating System :: OS Independent
